{
	"class" : {
		"monthOfYear:dayNumber:" : "mx 2/17/2008 21:10",
		"monthOfYear:dayNumber:calendar:" : "mx 2/17/2008 21:10",
		"monthOfYearWithYearNumber:monthNumber:calendar:" : "mx 2/19/2008 21:15",
		"year:month:dayNumber:" : "mx 2/17/2008 21:11",
		"yearNumber:month:dayNumber:" : "mx 2/17/2008 21:08",
		"yearNumber:monthNumber:dayNumber:calendar:" : "mx 2/17/2008 21:09" },
	"instance" : {
		"<" : "MaximilianoTaborda 5/24/2014 14:43",
		"=" : "mx 5/12/2007 16:26",
		"asGregorian" : "mx 2/17/2008 22:30",
		"asHebrew" : "mx 2/17/2008 22:31",
		"asIslamic" : "mx 2/17/2008 22:31",
		"asJulian" : "mx 2/17/2008 22:31",
		"asSmalltalkDate" : "mx 2/17/2008 22:31",
		"at:" : "MaximilianoTaborda 9/25/2014 22:15",
		"atTimeOfDay:" : "mx 5/12/2007 15:48",
		"calendar" : "mx 2/17/2008 22:31",
		"day" : "mx 2/17/2008 22:31",
		"dayNumber" : "mx 2/17/2008 20:59",
		"dayNumberFromEpoch" : "mx 2/17/2008 22:32",
		"dayOfMonth" : "mx 5/20/2007 15:54",
		"firstTimeOfDay" : "MaximilianoTaborda 9/20/2014 13:11",
		"hash" : "mx 5/12/2007 16:20",
		"includes:" : "mx 5/12/2007 16:06",
		"initializeMonthOfYear:dayNumber:calendar:" : "mx 2/17/2008 21:07",
		"isFirstDayOfMonth" : "mx 5/12/2007 16:08",
		"isFirstDayOfYear" : "mx 5/12/2007 16:08",
		"isLastDayOfMonth" : "mx 5/12/2007 16:07",
		"isLastDayOfYear" : "mx 5/12/2007 16:06",
		"lastTimeOfDay" : "MaximilianoTaborda 9/20/2014 13:11",
		"monthOfYear" : "mx 2/17/2008 20:59",
		"next:" : "mx 2/17/2008 22:32",
		"nextMonth:" : "mx 5/12/2007 16:02",
		"numberOfDaysFromBeginningOfMonth" : "MaximilianoTaborda 5/15/2014 00:52",
		"numberOfDaysFromBeginningOfYear" : "mx 5/12/2007 15:49",
		"numberOfDaysFromEpoch" : "mx 2/17/2008 22:32",
		"numberOfDaysToEndOfMonth" : "MaximilianoTaborda 5/15/2014 00:53",
		"numberOfDaysToEndOfYear" : "mx 5/12/2007 15:50",
		"printOn:" : "mx 5/12/2007 16:05" } }
